MANIFEST.in
README.txt
setup.py
oblige.egg-info/PKG-INFO
oblige.egg-info/SOURCES.txt
oblige.egg-info/dependency_links.txt
oblige.egg-info/top_level.txt
pyoblige/__init__.py
pyoblige/oblige.py
pyoblige/wad_configs.py
pyoblige/Oblige_src/Makefile
pyoblige/Oblige_src/Makefile.macos
pyoblige/Oblige_src/Makefile.xming
pyoblige/Oblige_src/addons/no_hang_lamp.pk3
pyoblige/Oblige_src/ajpoly_src/ajpoly.h
pyoblige/Oblige_src/ajpoly_src/pl_endian.h
pyoblige/Oblige_src/ajpoly_src/pl_local.h
pyoblige/Oblige_src/ajpoly_src/pl_map.cc
pyoblige/Oblige_src/ajpoly_src/pl_map.h
pyoblige/Oblige_src/ajpoly_src/pl_poly.cc
pyoblige/Oblige_src/ajpoly_src/pl_structs.h
pyoblige/Oblige_src/ajpoly_src/pl_util.cc
pyoblige/Oblige_src/ajpoly_src/pl_util.h
pyoblige/Oblige_src/ajpoly_src/pl_wad.cc
pyoblige/Oblige_src/ajpoly_src/pl_wad.h
pyoblige/Oblige_src/changelogs/085.txt
pyoblige/Oblige_src/changelogs/094.txt
pyoblige/Oblige_src/changelogs/097.txt
pyoblige/Oblige_src/changelogs/343.txt
pyoblige/Oblige_src/changelogs/347.txt
pyoblige/Oblige_src/changelogs/351.txt
pyoblige/Oblige_src/changelogs/357.txt
pyoblige/Oblige_src/changelogs/428.txt
pyoblige/Oblige_src/changelogs/605.txt
pyoblige/Oblige_src/changelogs/610.txt
pyoblige/Oblige_src/changelogs/620.txt
pyoblige/Oblige_src/changelogs/750.txt
pyoblige/Oblige_src/changelogs/7666.txt
pyoblige/Oblige_src/data/logo1.tga
pyoblige/Oblige_src/data/bg/airduct.tga
pyoblige/Oblige_src/data/bg/block1.tga
pyoblige/Oblige_src/data/bg/block2.tga
pyoblige/Oblige_src/data/bg/cement.tga
pyoblige/Oblige_src/data/bg/lamp1.tga
pyoblige/Oblige_src/data/bg/lamp2.tga
pyoblige/Oblige_src/data/bg/lamp3.tga
pyoblige/Oblige_src/data/masks/compgreen.tga
pyoblige/Oblige_src/data/masks/fireblu.tga
pyoblige/Oblige_src/data/masks/groovy1.tga
pyoblige/Oblige_src/data/masks/redrock.tga
pyoblige/Oblige_src/data/masks/shawn_r.tga
pyoblige/Oblige_src/data/masks/yellowish.tga
pyoblige/Oblige_src/engines/boom.lua
pyoblige/Oblige_src/engines/fs_things.lua
pyoblige/Oblige_src/engines/xlat.lua
pyoblige/Oblige_src/engines/zdoom.lua
pyoblige/Oblige_src/games/doom/base.lua
