Metadata-Version: 1.1
Name: oblige
Version: 0.1.1
Summary: Level generator for DOOM
Home-page: https://github.com/mwydmuch/PyOblige
Author: Marek Wydmuch, Michał Kempka
Author-email: vizdoom@googlegroups.com
License: UNKNOWN
Platform: Linux
Platform: Mac OS-X
Classifier: Development Status :: 3 - Alpha
Classifier: Intended Audience :: Science/Research
Classifier: Topic :: Scientific/Engineering :: Artificial Intelligence
Classifier: License :: OSI Approved :: GNU General Public License (GPL)
Classifier: Programming Language :: Python :: 2.7
Classifier: Programming Language :: Python :: 3.4
Classifier: Programming Language :: Python :: 3.5
Classifier: Programming Language :: Python :: 3.6
